tfc_apply_replace-1.0.3.data/data/requirements.txt
tfcar/__init__.py
tfcar/cli.py
tfc_apply_replace-1.0.3.dist-info/METADATA
tfc_apply_replace-1.0.3.dist-info/WHEEL
tfc_apply_replace-1.0.3.dist-info/entry_points.txt
tfc_apply_replace-1.0.3.dist-info/top_level.txt
tfc_apply_replace-1.0.3.dist-info/RECORD
