Metadata-Version: 2.1
Name: tfc-apply-replace
Version: 1.0.3
Summary: Tool to perform dynamic terraform applies w/replacement on TFC using resource name keywords.
Home-page: https://github.com/djschnei21/tfc-ws-apply-replace
License: UNKNOWN
Project-URL: Bug Tracker, https://github.com/djschnei21/tfc-ws-apply-replace/issues
Platform: UNKNOWN
Classifier: Environment :: Console
Classifier: Programming Language :: Python :: 3.7
Classifier: Programming Language :: Python :: 3.8
Classifier: Programming Language :: Python :: 3.9
Classifier: Programming Language :: Python :: 3.10
Classifier: License :: OSI Approved :: MIT License
Classifier: Operating System :: OS Independent
Requires-Python: >=3.7
Requires-Dist: terrasnek (==0.1.6)
